steamspypi/__init__.py
steamspypi/api.py
steamspypi/compatibility.py
steamspypi/download.py
steamspypi/download_all.py
steamspypi/load.py
steamspypi/utils.py
steamspypi/tests/__init__.py
steamspypi/tests/test_api.py
steamspypi/tests/test_compatibility.py
steamspypi/tests/test_download.py
steamspypi/tests/test_load.py
steamspypi/tests/test_utils.py
steamspypi-1.1.1.dist-info/LICENSE
steamspypi-1.1.1.dist-info/METADATA
steamspypi-1.1.1.dist-info/WHEEL
steamspypi-1.1.1.dist-info/top_level.txt
steamspypi-1.1.1.dist-info/RECORD
