Metadata-Version: 2.1
Name: steamspypi
Version: 1.1.1
Summary: SteamSpy API on PyPI
Home-page: https://github.com/woctezuma/steamspypi
Author: Wok
Author-email: wok@tuta.io
License: UNKNOWN
Download-URL: https://github.com/woctezuma/steamspypi/archive/1.1.1.tar.gz
Keywords: steam,steamspy,api
Platform: UNKNOWN
Classifier: Development Status :: 2 - Pre-Alpha
Classifier: Topic :: Games/Entertainment
Classifier: Programming Language :: Python :: 3
Classifier: License :: OSI Approved :: MIT License
Classifier: Operating System :: OS Independent
Requires-Python: >=3
